virtuinbridge/__init__.py
virtuinbridge/anduinrestserver.py
virtuinbridge/anduinxmlserver.py
virtuinbridge/balenabridge.py
virtuinbridge/helper.py
virtuinbridge/virtuinbridge.py
virtuinbridge/virtuinglobalstubs.py
VirtuinBridge-1.0.0.dist-info/LICENSE.md
VirtuinBridge-1.0.0.dist-info/METADATA
VirtuinBridge-1.0.0.dist-info/WHEEL
VirtuinBridge-1.0.0.dist-info/top_level.txt
VirtuinBridge-1.0.0.dist-info/zip-safe
VirtuinBridge-1.0.0.dist-info/RECORD
